pyrunit/__init__.py
pyrunit/arg.py
pyrunit/pyrunit.py
pyrunit-0.1.0.dist-info/LICENSE
pyrunit-0.1.0.dist-info/METADATA
pyrunit-0.1.0.dist-info/WHEEL
pyrunit-0.1.0.dist-info/entry_points.txt
pyrunit-0.1.0.dist-info/top_level.txt
pyrunit-0.1.0.dist-info/RECORD
