Metadata-Version: 2.1
Name: pyrunit
Version: 0.1.0
Summary: Simple shortcut to manage runit service
Home-page: https://gitlab.com/nesstero/pyrunit
Author: nestero
Author-email: nestero@mail.com
License: MIT
Platform: UNKNOWN
License-File: LICENSE
